LICENSE
py_lapper/__init__.py
py_lapper/lib.py
py_lapper-0.9.5.dist-info/LICENSE
py_lapper-0.9.5.dist-info/WHEEL
py_lapper-0.9.5.dist-info/METADATA
py_lapper-0.9.5.dist-info/RECORD
