Metadata-Version: 2.1
Name: py-lapper
Version: 0.9.5
Summary: A pure python port of nim-lapper.
Home-page: https://github.com/sstadick/py-lapper
License: MIT
Keywords: intervals,bioinformatics,algorithm
Author: Seth Stadick
Author-email: sstadick@gmail.com
Requires-Python: >=3.6,<4.0
Classifier: License :: OSI Approved :: MIT License
Classifier: Programming Language :: Python :: 3
Classifier: Programming Language :: Python :: 3.6
Classifier: Programming Language :: Python :: 3.7
Classifier: Programming Language :: Python :: 3.8
Project-URL: Repository, https://github.com/sstadick/py-lapper
